sd_fail_notify/__init__.py
sd_fail_notify/main.py
sd_fail_notify-19.12.0.dist-info/entry_points.txt
sd_fail_notify-19.12.0.dist-info/LICENSE
sd_fail_notify-19.12.0.dist-info/WHEEL
sd_fail_notify-19.12.0.dist-info/METADATA
sd_fail_notify-19.12.0.dist-info/RECORD
